kista/__init__.py
kista/__main__.py
kista-1.1.0.dist-info/LICENSE
kista-1.1.0.dist-info/METADATA
kista-1.1.0.dist-info/WHEEL
kista-1.1.0.dist-info/top_level.txt
kista-1.1.0.dist-info/zip-safe
kista-1.1.0.dist-info/RECORD
