Metadata-Version: 2.1
Name: kista
Version: 1.1.0
Summary: miscellaneous stuff, old norse for bag
Home-page: https://github.com/circleclick-labs/kista.git
Author: Joel Ward
Author-email: jmward+python@gmail.com
License: MIT
Platform: UNKNOWN
Classifier: Programming Language :: Python :: 3
Classifier: License :: OSI Approved :: MIT License
Classifier: Operating System :: OS Independent
Requires-Dist: web3
Requires-Dist: docopt
